lena/__init__.py
lena/context/__init__.py
lena/context/context.py
lena/context/functions.py
lena/context/update_context.py
lena/core/__init__.py
lena/core/adapters.py
lena/core/check_sequence_type.py
lena/core/exceptions.py
lena/core/fill_compute_seq.py
lena/core/fill_request_seq.py
lena/core/fill_seq.py
lena/core/functions.py
lena/core/lena_sequence.py
lena/core/meta.py
lena/core/sequence.py
lena/core/source.py
lena/core/split.py
lena/flow/__init__.py
lena/flow/cache.py
lena/flow/drop_context.py
lena/flow/elements.py
lena/flow/filter.py
lena/flow/functions.py
lena/flow/group_by.py
lena/flow/group_plots.py
lena/flow/group_scale.py
lena/flow/iterators.py
lena/flow/print_.py
lena/flow/progress.py
lena/flow/selectors.py
lena/flow/split_into_bins.py
lena/flow/zip.py
lena/input/__init__.py
lena/input/read_root_file.py
lena/input/read_root_tree.py
lena/math/__init__.py
lena/math/elements.py
lena/math/meshes.py
lena/math/utils.py
lena/math/vector3.py
lena/output/__init__.py
lena/output/latex_to_pdf.py
lena/output/make_filename.py
lena/output/pdf_to_png.py
lena/output/render_latex.py
lena/output/to_csv.py
lena/output/write.py
lena/output/write_root_tree.py
lena/output/writer.py
lena/structures/__init__.py
lena/structures/elements.py
lena/structures/graph.py
lena/structures/hist_functions.py
lena/structures/histogram.py
lena/structures/numpy_histogram.py
lena/structures/root_graphs.py
lena/structures/split_into_bins.py
lena/variables/__init__.py
lena/variables/functions.py
lena/variables/variable.py
lena-0.5.dist-info/LICENSE
lena-0.5.dist-info/METADATA
lena-0.5.dist-info/WHEEL
lena-0.5.dist-info/top_level.txt
lena-0.5.dist-info/RECORD
