Metadata-Version: 2.1
Name: lena
Version: 0.5
Summary: Lena is an architectural framework for data analysis
Home-page: https://github.com/ynikitenko/lena
Author: Yaroslav Nikitenko
Author-email: metst13@gmail.com
License: UNKNOWN
Project-URL: Documentation, https://lena.readthedocs.io
Project-URL: Source, https://github.com/ynikitenko/lena
Project-URL: Tracker, https://github.com/ynikitenko/lena/issues
Keywords: data analysis framework
Platform: UNKNOWN
Classifier: Development Status :: 4 - Beta
Classifier: Environment :: Console
Classifier: Intended Audience :: Developers
Classifier: Intended Audience :: Science/Research
Classifier: Programming Language :: Python
Classifier: Programming Language :: Python :: 2.7
Classifier: Programming Language :: Python :: 3.5
Classifier: Programming Language :: Python :: 3.6
Classifier: Programming Language :: Python :: 3.7
Classifier: Programming Language :: Python :: 3.8
Classifier: Programming Language :: Python :: 3.9
Classifier: Programming Language :: Python :: 3.10
Classifier: Programming Language :: Python :: Implementation :: PyPy
Classifier: Topic :: Scientific/Engineering :: Information Analysis
Classifier: Topic :: Software Development :: Libraries
Classifier: License :: OSI Approved :: Apache Software License
Classifier: Operating System :: OS Independent
Requires-Python: >=2.7
License-File: LICENSE
